mdciao/__init__.py
mdciao/dihedrals.py
mdciao/parsers.py
mdciao/cli/__init__.py
mdciao/cli/cli.py
mdciao/contacts/__init__.py
mdciao/contacts/_md_compute_contacts.py
mdciao/contacts/_progress.py
mdciao/contacts/contacts.py
mdciao/examples/01.Tutorial.ipynb
mdciao/examples/02.Missing_Contacts.ipynb
mdciao/examples/03.Comparing_CGs_Bars.ipynb
mdciao/examples/04.Comparing_CGs_Flares.ipynb
mdciao/examples/05.Flareplot_Schemes.ipynb
mdciao/examples/06.MSA_via_Consensus_Labels.ipynb
mdciao/examples/07.EGFR_Kinase_Inhibitors.ipynb
mdciao/examples/08.Manuscript.ipynb
mdciao/examples/09.Consensus_Labels.ipynb
mdciao/examples/__init__.py
mdciao/examples/examples.py
mdciao/filenames/__init__.py
mdciao/filenames/filenames.py
mdciao/flare/__init__.py
mdciao/flare/_textutils.py
mdciao/flare/_utils.py
mdciao/flare/flare.py
mdciao/fragments/__init__.py
mdciao/fragments/fragments.py
mdciao/nomenclature/__init__.py
mdciao/nomenclature/_md_from_dataframe.py
mdciao/nomenclature/nomenclature.py
mdciao/pdb/__init__.py
mdciao/pdb/pdb.py
mdciao/plots/__init__.py
mdciao/plots/plots.py
mdciao/sites/__init__.py
mdciao/sites/siteIO.py
mdciao/utils/COM.py
mdciao/utils/__init__.py
mdciao/utils/bonds.py
mdciao/utils/contact_matrix.py
mdciao/utils/lists.py
mdciao/utils/residue_and_atom.py
mdciao/utils/sequence.py
mdciao/utils/str_and_dict.py
mdciao-1.0.0.data/data/data_for_mdciao/RCSB_pdb/3E8D.pdb.gz
mdciao-1.0.0.data/data/data_for_mdciao/RCSB_pdb/3SN6.pdb.gz
mdciao-1.0.0.data/data/data_for_mdciao/examples/gs-b2ar.noH.pdb
mdciao-1.0.0.data/data/data_for_mdciao/examples/gs-b2ar.noH.stride.5.xtc
mdciao-1.0.0.data/data/data_for_mdciao/json/tip.json
mdciao-1.0.0.data/data/data_for_mdciao/nomenclature/KLIFS_P31751.xlsx
mdciao-1.0.0.data/data/data_for_mdciao/nomenclature/adrb2_human.xlsx
mdciao-1.0.0.data/data/data_for_mdciao/nomenclature/gnas2_human.xlsx
mdciao-1.0.0.data/data/data_for_mdciao/nomenclature/nomenclature.bib
mdciao-1.0.0.data/data/data_for_mdciao/notebooks/01.Tutorial.ipynb
mdciao-1.0.0.dist-info/LICENSE.txt
mdciao-1.0.0.dist-info/METADATA
mdciao-1.0.0.dist-info/WHEEL
mdciao-1.0.0.dist-info/top_level.txt
mdciao-1.0.0.dist-info/RECORD
