Metadata-Version: 2.2
Name: mdciao
Version: 1.0.0
Summary: mdciao: Accessible Analysis and Visualization of Molecular Dynamics Simulation Data
Author-email: Guillermo Perez-Hernandez <guillermo.perez@charite.de>
Project-URL: Homepage, https://github.com/gph82/mdciao
Project-URL: docs, https://mdciao.org
Classifier: Development Status :: 4 - Beta
Classifier: Programming Language :: Python :: 3
Classifier: Operating System :: OS Independent
Classifier: Intended Audience :: Science/Research
Classifier: License :: OSI Approved :: GNU Lesser General Public License v3 or later (LGPLv3+)
Classifier: Topic :: Scientific/Engineering :: Chemistry
Classifier: Topic :: Scientific/Engineering :: Bio-Informatics
Classifier: Topic :: Scientific/Engineering :: Visualization
Requires-Python: >=3.6
License-File: LICENSE.txt
Requires-Dist: cython
Requires-Dist: numpy<2; python_version <= "3.9"
Requires-Dist: numpy>=1.18.1
Requires-Dist: bezier
Requires-Dist: mdtraj>=1.9.8
Requires-Dist: astunparse; python_version != "3.8"
Requires-Dist: astunparse<1.6.3; python_version == "3.8"
Requires-Dist: pandas
Requires-Dist: matplotlib<=3.5.3; python_version < "3.8"
Requires-Dist: scipy<=1.9.0; python_version <= "3.8"
Requires-Dist: scipy
Requires-Dist: joblib
Requires-Dist: openpyxl
Requires-Dist: biopython>=1.77
Requires-Dist: ipython<=8.12; python_version <= "3.8"
Requires-Dist: ipython==7.*; python_version == "3.7"
Requires-Dist: ipython
Requires-Dist: XlsxWriter
Requires-Dist: requests
Requires-Dist: tqdm
Requires-Dist: ipywidgets
Requires-Dist: natsort
Requires-Dist: mpl_chord_diagram>=0.3.2
Requires-Dist: docstring_parser
